freeflow_llm/__init__.py
freeflow_llm/client.py
freeflow_llm/config.py
freeflow_llm/exceptions.py
freeflow_llm/models.py
freeflow_llm/utils.py
freeflow_llm/providers/__init__.py
freeflow_llm/providers/base.py
freeflow_llm/providers/gemini.py
freeflow_llm/providers/groq.py
freeflow_llm-0.1.3.dist-info/licenses/LICENSE
freeflow_llm-0.1.3.dist-info/METADATA
freeflow_llm-0.1.3.dist-info/WHEEL
freeflow_llm-0.1.3.dist-info/top_level.txt
freeflow_llm-0.1.3.dist-info/RECORD
