Metadata-Version: 2.4
Name: freeflow-llm
Version: 0.1.3
Summary: Chain multiple free-tier LLM APIs with automatic rate limit fallback
Author: FreeFlow Contributors
License: MIT
Project-URL: Homepage, https://github.com/thesecondchance/freeflow-llm
Project-URL: Repository, https://github.com/thesecondchance/freeflow-llm
Project-URL: Documentation, https://github.com/thesecondchance/freeflow-llm#readme
Project-URL: Bug Tracker, https://github.com/thesecondchance/freeflow-llm/issues
Keywords: llm,ai,free-tier,groq,gemini,mistral,rate-limit
Classifier: Development Status :: 3 - Alpha
Classifier: Intended Audience :: Developers
Classifier: License :: OSI Approved :: MIT License
Classifier: Programming Language :: Python :: 3
Classifier: Programming Language :: Python :: 3.9
Classifier: Programming Language :: Python :: 3.10
Classifier: Programming Language :: Python :: 3.11
Classifier: Programming Language :: Python :: 3.12
Classifier: Topic :: Software Development :: Libraries :: Python Modules
Classifier: Topic :: Scientific/Engineering :: Artificial Intelligence
Requires-Python: >=3.9
License-File: LICENSE
Requires-Dist: httpx>=0.25.0
Requires-Dist: python-dotenv>=1.0.0
Provides-Extra: dev
Requires-Dist: pytest>=7.0.0; extra == "dev"
Requires-Dist: pytest-cov>=4.0.0; extra == "dev"
Requires-Dist: pytest-asyncio>=0.21.0; extra == "dev"
Requires-Dist: black>=23.0.0; extra == "dev"
Requires-Dist: ruff>=0.1.0; extra == "dev"
Requires-Dist: mypy>=1.0.0; extra == "dev"
Dynamic: license-file
